odoo/addons/stock_mts_mto_rule_mrp/README.rst
odoo/addons/stock_mts_mto_rule_mrp/__init__.py
odoo/addons/stock_mts_mto_rule_mrp/__manifest__.py
odoo/addons/stock_mts_mto_rule_mrp/i18n/it.po
odoo/addons/stock_mts_mto_rule_mrp/i18n/stock_mts_mto_rule_mrp.pot
odoo/addons/stock_mts_mto_rule_mrp/models/__init__.py
odoo/addons/stock_mts_mto_rule_mrp/models/mrp_production.py
odoo/addons/stock_mts_mto_rule_mrp/readme/CONFIGURE.rst
odoo/addons/stock_mts_mto_rule_mrp/readme/CONTRIBUTORS.rst
odoo/addons/stock_mts_mto_rule_mrp/readme/DESCRIPTION.rst
odoo/addons/stock_mts_mto_rule_mrp/readme/HISTORY.rst
odoo/addons/stock_mts_mto_rule_mrp/readme/USAGE.rst
odoo/addons/stock_mts_mto_rule_mrp/static/description/icon.png
odoo/addons/stock_mts_mto_rule_mrp/static/description/index.html
odoo/addons/stock_mts_mto_rule_mrp/tests/__init__.py
odoo/addons/stock_mts_mto_rule_mrp/tests/test_mto_mts_route_mrp.py
odoo12_addon_stock_mts_mto_rule_mrp-12.0.1.0.0.99.dev7.dist-info/METADATA
odoo12_addon_stock_mts_mto_rule_mrp-12.0.1.0.0.99.dev7.dist-info/WHEEL
odoo12_addon_stock_mts_mto_rule_mrp-12.0.1.0.0.99.dev7.dist-info/top_level.txt
odoo12_addon_stock_mts_mto_rule_mrp-12.0.1.0.0.99.dev7.dist-info/RECORD
