Metadata-Version: 2.1
Name: odoo12-addon-stock-mts-mto-rule-mrp
Version: 12.0.1.0.0.99.dev7
Summary: Add support for MTS+MTO route on manufacturing
Home-page: https://github.com/OCA/manufacture
Author: Camptocamp,Odoo Community Association (OCA)
Author-email: support@odoo-community.org
License: AGPL-3
Platform: UNKNOWN
Classifier: Programming Language :: Python
Classifier: Framework :: Odoo
Classifier: Framework :: Odoo :: 12.0
Classifier: License :: OSI Approved :: GNU Affero General Public License v3
Classifier: Development Status :: 3 - Alpha
Requires-Python: >=3.5
Requires-Dist: odoo12-addon-stock-mts-mto-rule
Requires-Dist: odoo <12.1dev,>=12.0a
